loggingredactor/__init__.py
loggingredactor/redacting_filter.py
loggingredactor-0.0.6.dist-info/LICENSE
loggingredactor-0.0.6.dist-info/METADATA
loggingredactor-0.0.6.dist-info/WHEEL
loggingredactor-0.0.6.dist-info/top_level.txt
loggingredactor-0.0.6.dist-info/RECORD
